PyHotKey/__init__.py
PyHotKey/_info.py
PyHotKey/_keyboard.py
PyHotKey/_keys.py
PyHotKey/_loggers.py
PyHotKey/_platform_stuff/__init__.py
PyHotKey/_platform_stuff/darwin.py
PyHotKey/_platform_stuff/uinput.py
PyHotKey/_platform_stuff/win32.py
PyHotKey/_platform_stuff/xorg.py
PyHotKey-1.5.2.dist-info/COPYING.LGPL
PyHotKey-1.5.2.dist-info/METADATA
PyHotKey-1.5.2.dist-info/WHEEL
PyHotKey-1.5.2.dist-info/top_level.txt
PyHotKey-1.5.2.dist-info/RECORD
