Metadata-Version: 2.1
Name: PyHotKey
Version: 1.5.2
Summary: A cross-platform keyboard module.
Home-page: https://github.com/Xpp521/PyHotKey
Author: Xpp
Author-email: xpp233@foxmail.com
License: LGPLv3
Project-URL: Documentation, https://github.com/Xpp521/PyHotKey
Project-URL: Source, https://github.com/Xpp521/PyHotKey
Project-URL: Tracker, https://github.com/Xpp521/PyHotKey/issues
Keywords: hotkey,keyboard,hot+key
Classifier: Development Status :: 5 - Production/Stable
Classifier: Operating System :: OS Independent
Classifier: Operating System :: MacOS :: MacOS X
Classifier: Operating System :: Microsoft :: Windows :: Windows NT/2000
Classifier: Operating System :: POSIX
Classifier: License :: OSI Approved :: GNU Lesser General Public License v3 (LGPLv3)
Classifier: Intended Audience :: Developers
Classifier: Programming Language :: Python
Classifier: Programming Language :: Python :: 3
Classifier: Programming Language :: Python :: 3.4
Classifier: Programming Language :: Python :: 3.5
Classifier: Programming Language :: Python :: 3.6
Classifier: Programming Language :: Python :: 3.7
Classifier: Programming Language :: Python :: 3.8
Classifier: Programming Language :: Python :: 3.9
Classifier: Programming Language :: Python :: 3.10
Classifier: Programming Language :: Python :: 3.11
Classifier: Programming Language :: Python :: 3.12
Classifier: Topic :: Software Development :: Libraries :: Python Modules
Classifier: Topic :: System :: Monitoring
License-File: COPYING.LGPL
Requires-Dist: pynput ==1.7.7
